old-doc/__init__.py
old-doc/old_doc.py
old-doc/pipeline.py
old_doc/__init__.py
old_doc/pipeline.py
old_doc-0.0.3.dist-info/LICENSE
old_doc-0.0.3.dist-info/METADATA
old_doc-0.0.3.dist-info/WHEEL
old_doc-0.0.3.dist-info/top_level.txt
old_doc-0.0.3.dist-info/RECORD
